ruid/__init__.py
ruid-0.1.2.dist-info/METADATA
ruid-0.1.2.dist-info/WHEEL
ruid-0.1.2.dist-info/RECORD
