Metadata-Version: 2.1
Name: ruid
Version: 0.1.2
Summary: Reasonably unique and readable identifier generator
Home-page: https://github.com/kashifpk/ruid
Author: Kashif Iftikhar
Author-email: kashif@compulife.com.pk
Requires-Python: >=3.8,<4.0
Classifier: Programming Language :: Python :: 3
Classifier: Programming Language :: Python :: 3.8
Classifier: Programming Language :: Python :: 3.9
Classifier: Programming Language :: Python :: 3.10
Classifier: Programming Language :: Python :: 3.11
Classifier: Programming Language :: Python :: 3.12
Project-URL: Repository, https://github.com/kashifpk/ruid
